decimify/__init__.py
decimify/parser.py
decimify/py.typed
decimify-0.3.0.dist-info/METADATA
decimify-0.3.0.dist-info/WHEEL
decimify-0.3.0.dist-info/licenses/LICENSE
decimify-0.3.0.dist-info/RECORD
